{
  "$schema": "https://json-schema.org/draft/2020-12/schema",
  "$id": "https://reliever.example.com/process/CAP.BSP.004.ENV/CMD.BSP.004.ENV.ALLOCATE_PERIOD_BUDGET/0.1.0/schema.json",
  "x-process-version": "0.1.0",
  "x-process-role": "command-payload",
  "x-process-capability": "CAP.BSP.004.ENV",
  "x-process-command": "CMD.BSP.004.ENV.ALLOCATE_PERIOD_BUDGET",
  "x-process-aggregate": "AGG.BSP.004.ENV.PERIOD_BUDGET",
  "x-process-correlation-key": "case_id",
  "x-process-idempotency-key": "trigger.event_id",
  "title": "CMD.BSP.004.ENV.ALLOCATE_PERIOD_BUDGET — Allocate the categorised period budget for a beneficiary",
  "description": "Payload of the ALLOCATE_PERIOD_BUDGET command. Issued by POL.BSP.004.ENV.ON_BENEFICIARY_ENROLLED on RVT.BSP.002.CASE_OPENED, handled by AGG.BSP.004.ENV.PERIOD_BUDGET. Emits one RVT.BSP.004.ENVELOPE_INITIALIZED per category in tier_snapshot. Idempotent on trigger.event_id over the lifetime of the period.",
  "type": "object",
  "additionalProperties": false,
  "required": ["case_id", "period_index", "period_start", "period_end", "tier_snapshot", "trigger"],
  "$defs": {
    "category_allocation": {
      "type": "object",
      "additionalProperties": false,
      "required": ["category", "cap_amount"],
      "properties": {
        "category": {
          "type": "string",
          "minLength": 1,
          "description": "Spending category covered by this envelope (e.g. ESSENTIAL_GROCERY, TRANSPORT)."
        },
        "cap_amount": {
          "type": "number",
          "exclusiveMinimum": 0,
          "description": "Maximum amount authorised for this envelope over the period (currency-neutral; programme currency assumed)."
        }
      }
    },
    "trigger": {
      "type": "object",
      "additionalProperties": false,
      "required": ["event_id"],
      "properties": {
        "event_id": {
          "type": "string",
          "minLength": 1,
          "description": "IDEMPOTENCY KEY. Identifier of the upstream resource event that caused this command."
        },
        "occurred_at": {
          "type": "string",
          "format": "date-time",
          "description": "Timestamp of the upstream fact (ISO-8601, UTC). Used for ordering, NOT for idempotency."
        }
      }
    }
  },
  "properties": {
    "case_id": {
      "type": "string",
      "minLength": 1,
      "description": "CORRELATION KEY. Reference to the participation case (Reliever case ID, owned by CAP.BSP.002.ENR)."
    },
    "period_index": {
      "type": "integer",
      "minimum": 0,
      "description": "Zero-based index of the period in the beneficiary's participation sequence. period_index = 0 at enrolment."
    },
    "period_start": {
      "type": "string",
      "format": "date",
      "description": "Inclusive start of the period."
    },
    "period_end": {
      "type": "string",
      "format": "date",
      "description": "Inclusive end of the period (when the period closes and unconsumed signals are emitted)."
    },
    "tier_snapshot": {
      "type": "object",
      "additionalProperties": false,
      "required": ["tier_id", "categories"],
      "description": "Snapshot of the active tier definition that drives the per-category caps. Sourced from CAP.REF.001.TIE.",
      "properties": {
        "tier_id": {
          "type": "string",
          "minLength": 1,
          "description": "Identifier of the tier (e.g. T1_INITIAL, T2_PROGRESSING)."
        },
        "categories": {
          "type": "array",
          "minItems": 1,
          "items": { "$ref": "#/$defs/category_allocation" },
          "description": "Non-empty list of (category, cap_amount) pairs; one envelope is created per entry."
        }
      }
    },
    "trigger": { "$ref": "#/$defs/trigger" }
  }
}
